json_annotate/__init__.py
json_annotate/main.py
json_annotate-0.1.2.dist-info/DESCRIPTION.rst
json_annotate-0.1.2.dist-info/entry_points.txt
json_annotate-0.1.2.dist-info/METADATA
json_annotate-0.1.2.dist-info/metadata.json
json_annotate-0.1.2.dist-info/RECORD
json_annotate-0.1.2.dist-info/top_level.txt
json_annotate-0.1.2.dist-info/WHEEL
