Metadata-Version: 2.0
Name: json-annotate
Version: 0.1.2
Summary: ..
Home-page: https://github.com/aronwc/json_annotate
Author: Aron Culotta
Author-email: aronwc@gmail.com
License: MIT license
Keywords: json_annotate
Platform: UNKNOWN
Classifier: Development Status :: 2 - Pre-Alpha
Classifier: Intended Audience :: Developers
Classifier: License :: OSI Approved :: MIT License
Classifier: Natural Language :: English
Classifier: Programming Language :: Python :: 3
Classifier: Programming Language :: Python :: 3.3
Classifier: Programming Language :: Python :: 3.4
Classifier: Programming Language :: Python :: 3.5
Requires-Dist: termcolor
